domainscout/GUI.py
domainscout/__init__.py
domainscout/appicon.ico
domainscout/export.py
domainscout/import.py
domainscout/whoisQuery.py
domainscout-1.4.data/data/icons/appicon.ico
domainscout-1.4.dist-info/METADATA
domainscout-1.4.dist-info/WHEEL
domainscout-1.4.dist-info/entry_points.txt
domainscout-1.4.dist-info/top_level.txt
domainscout-1.4.dist-info/RECORD
