Metadata-Version: 2.4
Name: DomainScout
Version: 1.4
Summary: A desktop GUI client to view discovered domains using known disposable emails in WHOIS contact records.
Home-page: https://derekrgreene.com
Author: Derek R. Greene
Author-email: derek@derekrgreene.com
Requires-Dist: requests
Requires-Dist: PyQt6
Requires-Dist: python-dotenv
Requires-Dist: python-whois
Dynamic: author
Dynamic: author-email
Dynamic: description
Dynamic: description-content-type
Dynamic: home-page
Dynamic: requires-dist
Dynamic: summary
